{"name":"自动配置","slug":"自动配置","count":2,"postlist":[{"title":"为什么你的 SpringBoot 自动配置失效了","uid":"0733c66f6904b8d3bf1d0aaecefb6227","slug":"springboot/springboot-series-autoconfigure-invalid","date":"2021-11-15T03:35:18.000Z","updated":"2024-07-05T04:09:05.827Z","comments":true,"path":"api/articles/springboot/springboot-series-autoconfigure-invalid.json","keywords":null,"cover":[],"text":"本文源自近期项目中遇到的问题， bug 总是出现在你自以为是的地方… 问题描述下面是一个简单复现的代码片段，在你没有阅读完本文时，如果能做出正确的判断，那恭喜你...","permalink":"/post/springboot/springboot-series-autoconfigure-invalid","photos":[],"count_time":{"symbolsCount":"6.8k","symbolsTime":"6 mins."},"categories":[{"name":"SpringBoot","slug":"SpringBoot","count":17,"path":"api/categories/SpringBoot.json"}],"tags":[{"name":"SpringBoot","slug":"SpringBoot","count":17,"path":"api/tags/SpringBoot.json"},{"name":"自动配置","slug":"自动配置","count":2,"path":"api/tags/自动配置.json"}],"author":{"name":"glmapper","slug":"blog-author","avatar":"https://glmapper-blog.oss-cn-hangzhou.aliyuncs.com/common/favicon.ico","link":"/","description":"开放，开源，分享，共享","socials":{"github":"https://github.com/glmapper","twitter":"","stackoverflow":"","wechat":"","qq":"","weibo":"https://weibo.com/u/2412872703","zhihu":"","csdn":"","juejin":"https://juejin.cn/user/3227821827961806","customs":{"sofastack":{"icon":"https://glmapper-blog.oss-cn-hangzhou.aliyuncs.com/common/sofastack.svg","link":"https://www.sofastack.tech/"}}}}},{"title":"SpringBoot 源码系列-自动配置及 starter 机制解析","uid":"e42097f5a6c0cf4efef189a5728220a9","slug":"springboot/springboot-series-auto-configure","date":"2020-01-05T08:36:19.000Z","updated":"2024-07-05T04:09:05.827Z","comments":true,"path":"api/articles/springboot/springboot-series-auto-configure.json","keywords":null,"cover":null,"text":" 一家之言，如有任何错误，请批评指出，不胜感激 本篇主要来讨论研究两个问题：1、什么自动配置，2、如何编写自动配置 在使用 Spring 作为项目开发框架的过程...","permalink":"/post/springboot/springboot-series-auto-configure","photos":[],"count_time":{"symbolsCount":"8.1k","symbolsTime":"7 mins."},"categories":[{"name":"SpringBoot","slug":"SpringBoot","count":17,"path":"api/categories/SpringBoot.json"}],"tags":[{"name":"SpringBoot","slug":"SpringBoot","count":17,"path":"api/tags/SpringBoot.json"},{"name":"自动配置","slug":"自动配置","count":2,"path":"api/tags/自动配置.json"},{"name":"starter 机制","slug":"starter-机制","count":1,"path":"api/tags/starter-机制.json"}],"author":{"name":"glmapper","slug":"blog-author","avatar":"https://glmapper-blog.oss-cn-hangzhou.aliyuncs.com/common/favicon.ico","link":"/","description":"开放，开源，分享，共享","socials":{"github":"https://github.com/glmapper","twitter":"","stackoverflow":"","wechat":"","qq":"","weibo":"https://weibo.com/u/2412872703","zhihu":"","csdn":"","juejin":"https://juejin.cn/user/3227821827961806","customs":{"sofastack":{"icon":"https://glmapper-blog.oss-cn-hangzhou.aliyuncs.com/common/sofastack.svg","link":"https://www.sofastack.tech/"}}}}}]}